casbin_pony_adapter/__init__.py
casbin_pony_adapter/adapter.py
casbin_pony_adapter/filter.py
casbin_pony_adapter-1.0.1.dist-info/LICENSE
casbin_pony_adapter-1.0.1.dist-info/METADATA
casbin_pony_adapter-1.0.1.dist-info/WHEEL
casbin_pony_adapter-1.0.1.dist-info/top_level.txt
casbin_pony_adapter-1.0.1.dist-info/RECORD
