Metadata-Version: 2.1
Name: casbin-pony-adapter
Version: 1.0.1
Summary: Pony ORM Adapter for PyCasbin
Home-page: https://github.com/drorvinkler/pycasbin-pony-adapter
Author: Dror A. Vinkler
License: MIT
Platform: UNKNOWN
Classifier: Programming Language :: Python :: 3
Classifier: License :: OSI Approved :: MIT License
Classifier: Operating System :: OS Independent
Requires-Python: >=3.7
Requires-Dist: pony
Requires-Dist: casbin
